[
    {
        "key": "dbln",
        "value": "%7B%2261566813392744%22%3A%22cP8wlN8x%22%7D",
        "domain": "facebook.com",
        "path": "/login/device-based/",
        "hostOnly": false,
        "creation": "2026-01-17T19:59:57.374Z",
        "lastAccessed": "2026-01-17T19:59:57.374Z"
    },
    {
        "key": "sb",
        "value": "aqn-Z7EMEWLa7q7fupuhtj9X",
        "domain": "facebook.com",
        "path": "/",
        "hostOnly": false,
        "creation": "2026-01-17T19:59:57.374Z",
        "lastAccessed": "2026-01-17T19:59:57.374Z"
    },
    {
        "key": "datr",
        "value": "4cA7aQZAa1hV6dZnmYl44mtG",
        "domain": "facebook.com",
        "path": "/",
        "hostOnly": false,
        "creation": "2026-01-17T19:59:57.374Z",
        "lastAccessed": "2026-01-17T19:59:57.374Z"
    },
    {
        "key": "dpr",
        "value": "2.1988937854766846",
        "domain": "facebook.com",
        "path": "/",
        "hostOnly": false,
        "creation": "2026-01-17T19:59:57.374Z",
        "lastAccessed": "2026-01-17T19:59:57.374Z"
    },
    {
        "key": "ps_l",
        "value": "1",
        "domain": "facebook.com",
        "path": "/",
        "hostOnly": false,
        "creation": "2026-01-17T19:59:57.374Z",
        "lastAccessed": "2026-01-17T19:59:57.374Z"
    },
    {
        "key": "ps_n",
        "value": "1",
        "domain": "facebook.com",
        "path": "/",
        "hostOnly": false,
        "creation": "2026-01-17T19:59:57.374Z",
        "lastAccessed": "2026-01-17T19:59:57.374Z"
    },
    {
        "key": "pas",
        "value": "61584694736902%3AY8WHHeK2vL%2C61566813392744%3A6QNmb4pvth",
        "domain": "facebook.com",
        "path": "/",
        "hostOnly": false,
        "creation": "2026-01-17T19:59:57.374Z",
        "lastAccessed": "2026-01-17T19:59:57.374Z"
    },
    {
        "key": "oo",
        "value": "v1",
        "domain": "facebook.com",
        "path": "/",
        "hostOnly": false,
        "creation": "2026-01-17T19:59:57.374Z",
        "lastAccessed": "2026-01-17T19:59:57.374Z"
    },
    {
        "key": "wd",
        "value": "891x1693",
        "domain": "facebook.com",
        "path": "/",
        "hostOnly": false,
        "creation": "2026-01-17T19:59:57.374Z",
        "lastAccessed": "2026-01-17T19:59:57.374Z"
    },
    {
        "key": "c_user",
        "value": "61566813392744",
        "domain": "facebook.com",
        "path": "/",
        "hostOnly": false,
        "creation": "2026-01-17T19:59:57.374Z",
        "lastAccessed": "2026-01-17T19:59:57.374Z"
    },
    {
        "key": "fr",
        "value": "1zLkQOMDkHHCcPlDR.AWfd2wgjUlz-U8kubr4Aa0YEbM4-Xe_0gS5syqX8cJee4exZ5qs.Bpa-pW..AAA.0.0.Bpa-pW.AWcWafWlm9dQR4g_CdUzeteGVwU",
        "domain": "facebook.com",
        "path": "/",
        "hostOnly": false,
        "creation": "2026-01-17T19:59:57.374Z",
        "lastAccessed": "2026-01-17T19:59:57.374Z"
    },
    {
        "key": "xs",
        "value": "49%3AlYvI3mRfFdFI-Q%3A2%3A1768680002%3A-1%3A-1%3A%3AAcy4i82fJkczfM19nA1j2pH0sUEQw58W6GkW2Tdy-Q",
        "domain": "facebook.com",
        "path": "/",
        "hostOnly": false,
        "creation": "2026-01-17T19:59:57.374Z",
        "lastAccessed": "2026-01-17T19:59:57.374Z"
    },
    {
        "key": "presence",
        "value": "C%7B%22t3%22%3A%5B%5D%2C%22utc3%22%3A1768679983545%2C%22v%22%3A1%7D",
        "domain": "facebook.com",
        "path": "/",
        "hostOnly": false,
        "creation": "2026-01-17T19:59:57.374Z",
        "lastAccessed": "2026-01-17T19:59:57.374Z"
    }
        ]
